{
  "framework_info": {
    "name": "Advanced Hull-Field Integration Analysis Framework",
    "version": "1.0.0",
    "purpose": "FTL Hull-Field Integration Analysis",
    "graviton_ecosystem_integration": true,
    "compliance": "Medical-grade safety protocols"
  },
  "integration_assessment": {
    "small_probe": {
      "comprehensive_integration_assessment": {
        "assessment_info": {
          "vessel_type": "small_probe",
          "assessment_date": "2025-07-11T19:47:06.274156",
          "vessel_configuration": {
            "dimensions": [
              15,
              3,
              2
            ],
            "crew_capacity": 0,
            "field_systems": [
              "FieldConfiguration(field_type=<FieldType.LQG_POLYMER: 'lqg_polymer'>, field_strength=0.6, coupling_strength=0.7, coherence_time=1e-06, energy_requirement=50, safety_margin=1000000.0, integration_level=<IntegrationLevel.ADVANCED: 'advanced'>)",
              "FieldConfiguration(field_type=<FieldType.STRUCTURAL_INTEGRITY: 'structural_integrity'>, field_strength=0.8, coupling_strength=0.9, coherence_time=0.001, energy_requirement=20, safety_margin=100000.0, integration_level=<IntegrationLevel.COMPLETE: 'complete'>)"
            ],
            "hull_material": "carbon_nanolattice",
            "safety_protocol": "SafetyProtocol.MEDICAL_GRADE"
          },
          "graviton_ecosystem_integration": true
        },
        "individual_analyses": {
          "lqg_polymer_coupling": {
            "lqg_polymer_coupling_analysis": {
              "input_parameters": {
                "hull_material": "carbon_nanolattice",
                "field_strength": 0.6,
                "polymer_discretization_scale_m": 1e-15
              },
              "coupling_characteristics": {
                "quantum_coupling_strength": 0.44999999999999996,
                "discretization_coupling_factor": 1.1111111110987658e-11,
                "enhanced_coupling_efficiency": 0.5601302190309042,
                "golden_ratio_enhancement": 24473.382006867614
              },
              "energy_analysis": {
                "polymer_energy_density_j_per_m3": 1667816998.6290557,
                "hull_stress_induced_pa": 61770.99994853797,
                "field_penetration_depth_m": 2.23606797749979e-15
              },
              "coherence_analysis": {
                "base_coherence_time_s": 1e-06,
                "hull_decoherence_rate": 0.15,
                "effective_coherence_time_s": 8.695652173913044e-07,
                "coherence_preservation": 0.8695652173913044
              },
              "resonance_analysis": {
                "resonance_frequencies_hz": [
                  6.703563152297506e+22,
                  1.3407126304595012e+23,
                  2.011068945689252e+23,
                  2.6814252609190024e+23,
                  3.351781576148753e+23
                ],
                "resonance_risk_level": "MEDIUM"
              },
              "safety_assessment": {
                "crew_exposure_estimate": 1.6678169986290558e-06,
                "crew_safety_factor": 5.995861661213426e+17,
                "medical_grade_compliant": true,
                "safety_level": "EXCELLENT"
              }
            }
          },
          "sif_integration": {
            "sif_integration_analysis": {
              "sif_parameters": {
                "baseline_strength": 0.8,
                "coverage_efficiency": 0.95,
                "response_time_s": 0.001
              },
              "field_interactions": {
                "lqg_polymer": {
                  "interaction_strength": 0.33599999999999997,
                  "interference_pattern": "quantum_coupled",
                  "energy_requirement_mw": 18.0,
                  "stress_enhancement_factor": 0.248064,
                  "safety_margin": 2976190.4761904767,
                  "integration_level": "advanced"
                },
                "structural_integrity": {
                  "interaction_strength": 1.6,
                  "interference_pattern": "constructive",
                  "energy_requirement_mw": 16.0,
                  "stress_enhancement_factor": 0.27840000000000004,
                  "safety_margin": 62500.0,
                  "integration_level": "complete"
                }
              },
              "system_analysis": {
                "total_energy_requirement_mw": 34.0,
                "coordination_efficiency": 0.7795187907884576,
                "optimized_coordination_efficiency": 0.7967023589022377,
                "maximum_stress_enhancement": 0.27840000000000004,
                "minimum_safety_margin": 62500.0,
                "worst_case_shutdown_time_s": 0.14285714285714288
              },
              "coupling_analysis": {
                "coupling_matrix": [
                  [
                    1.0,
                    0.315
                  ],
                  [
                    0.504,
                    1.0
                  ]
                ],
                "max_eigenvalue": 1.3984469851812158,
                "system_stable": "True",
                "stability_assessment": "STABLE"
              },
              "golden_ratio_optimization": {
                "sif_enhancement_factor": 2204.3815129073973,
                "coordination_improvement": "2.2%"
              }
            }
          },
          "emergency_protocols": {
            "emergency_protocol_analysis": {
              "vessel_configuration": {
                "dimensions": [
                  15,
                  3,
                  2
                ],
                "crew_capacity": 0,
                "field_systems": [
                  "FieldConfiguration(field_type=<FieldType.LQG_POLYMER: 'lqg_polymer'>, field_strength=0.6, coupling_strength=0.7, coherence_time=1e-06, energy_requirement=50, safety_margin=1000000.0, integration_level=<IntegrationLevel.ADVANCED: 'advanced'>)",
                  "FieldConfiguration(field_type=<FieldType.STRUCTURAL_INTEGRITY: 'structural_integrity'>, field_strength=0.8, coupling_strength=0.9, coherence_time=0.001, energy_requirement=20, safety_margin=100000.0, integration_level=<IntegrationLevel.COMPLETE: 'complete'>)"
                ],
                "hull_material": "carbon_nanolattice",
                "safety_protocol": "SafetyProtocol.MEDICAL_GRADE"
              },
              "threat_scenarios": {
                "field_cascade_failure": {
                  "description": "Multiple field systems fail simultaneously",
                  "probability": 1e-06,
                  "severity": "CRITICAL",
                  "response_time_required": 0.1,
                  "crew_danger_level": "HIGH"
                },
                "hull_breach_with_field_loss": {
                  "description": "Hull breach causes field system failure",
                  "probability": 1e-07,
                  "severity": "CATASTROPHIC",
                  "response_time_required": 0.05,
                  "crew_danger_level": "EXTREME"
                },
                "lqg_polymer_instability": {
                  "description": "LQG polymer field becomes unstable",
                  "probability": 1e-05,
                  "severity": "HIGH",
                  "response_time_required": 0.5,
                  "crew_danger_level": "MEDIUM"
                },
                "sif_overload": {
                  "description": "Structural Integrity Field overloads",
                  "probability": 0.0001,
                  "severity": "MEDIUM",
                  "response_time_required": 1.0,
                  "crew_danger_level": "LOW"
                },
                "quantum_decoherence_event": {
                  "description": "Quantum coherence loss in field systems",
                  "probability": 0.001,
                  "severity": "LOW",
                  "response_time_required": 10.0,
                  "crew_danger_level": "MINIMAL"
                }
              },
              "response_protocols": {
                "field_cascade_failure": {
                  "threat_details": {
                    "description": "Multiple field systems fail simultaneously",
                    "probability": 1e-06,
                    "severity": "CRITICAL",
                    "response_time_required": 0.1,
                    "crew_danger_level": "HIGH"
                  },
                  "assigned_protocol": "emergency",
                  "response_time_analysis": {
                    "required_time_s": 0.1,
                    "available_time_s": 0.1,
                    "response_adequate": true,
                    "time_margin_s": 0.0
                  },
                  "response_actions": [
                    "Immediate field system isolation",
                    "Emergency power redistribution",
                    "Backup field activation",
                    "Complete system shutdown",
                    "Emergency life support",
                    "Distress signal transmission"
                  ],
                  "crew_protection_measures": [
                    "Immediate isolation chamber activation",
                    "Medical monitoring enhancement",
                    "Emergency medical preparation"
                  ],
                  "ecosystem_integration": {
                    "graviton_manufacturing_alerts": true,
                    "cross_system_coordination": true,
                    "medical_facility_notification": true,
                    "emergency_support_request": true
                  },
                  "medical_grade_compliance": true
                },
                "hull_breach_with_field_loss": {
                  "threat_details": {
                    "description": "Hull breach causes field system failure",
                    "probability": 1e-07,
                    "severity": "CATASTROPHIC",
                    "response_time_required": 0.05,
                    "crew_danger_level": "EXTREME"
                  },
                  "assigned_protocol": "emergency",
                  "response_time_analysis": {
                    "required_time_s": 0.05,
                    "available_time_s": 0.1,
                    "response_adequate": false,
                    "time_margin_s": 0.05
                  },
                  "response_actions": [
                    "Immediate field system isolation",
                    "Emergency power redistribution",
                    "Backup field activation",
                    "Hull breach containment",
                    "Emergency atmospheric systems",
                    "Crew evacuation protocols"
                  ],
                  "crew_protection_measures": [
                    "Immediate isolation chamber activation",
                    "Medical monitoring enhancement",
                    "Emergency medical preparation"
                  ],
                  "ecosystem_integration": {
                    "graviton_manufacturing_alerts": true,
                    "cross_system_coordination": true,
                    "medical_facility_notification": true,
                    "emergency_support_request": true
                  },
                  "medical_grade_compliance": true
                },
                "lqg_polymer_instability": {
                  "threat_details": {
                    "description": "LQG polymer field becomes unstable",
                    "probability": 1e-05,
                    "severity": "HIGH",
                    "response_time_required": 0.5,
                    "crew_danger_level": "MEDIUM"
                  },
                  "assigned_protocol": "ftl_grade",
                  "response_time_analysis": {
                    "required_time_s": 0.5,
                    "available_time_s": 3,
                    "response_adequate": false,
                    "time_margin_s": 2.5
                  },
                  "response_actions": [],
                  "crew_protection_measures": [
                    "Enhanced radiation shielding",
                    "Medical monitoring increase"
                  ],
                  "ecosystem_integration": {
                    "graviton_manufacturing_alerts": true,
                    "cross_system_coordination": true,
                    "medical_facility_notification": true,
                    "emergency_support_request": true
                  },
                  "medical_grade_compliance": true
                },
                "sif_overload": {
                  "threat_details": {
                    "description": "Structural Integrity Field overloads",
                    "probability": 0.0001,
                    "severity": "MEDIUM",
                    "response_time_required": 1.0,
                    "crew_danger_level": "LOW"
                  },
                  "assigned_protocol": "medical_grade",
                  "response_time_analysis": {
                    "required_time_s": 1.0,
                    "available_time_s": 30,
                    "response_adequate": false,
                    "time_margin_s": 29.0
                  },
                  "response_actions": [],
                  "crew_protection_measures": [
                    "Standard monitoring continuation"
                  ],
                  "ecosystem_integration": {
                    "graviton_manufacturing_alerts": true,
                    "cross_system_coordination": true,
                    "medical_facility_notification": true,
                    "emergency_support_request": true
                  },
                  "medical_grade_compliance": true
                },
                "quantum_decoherence_event": {
                  "threat_details": {
                    "description": "Quantum coherence loss in field systems",
                    "probability": 0.001,
                    "severity": "LOW",
                    "response_time_required": 10.0,
                    "crew_danger_level": "MINIMAL"
                  },
                  "assigned_protocol": "medical_grade",
                  "response_time_analysis": {
                    "required_time_s": 10.0,
                    "available_time_s": 30,
                    "response_adequate": false,
                    "time_margin_s": 20.0
                  },
                  "response_actions": [],
                  "crew_protection_measures": [
                    "Standard monitoring continuation"
                  ],
                  "ecosystem_integration": {
                    "graviton_manufacturing_alerts": true,
                    "cross_system_coordination": true,
                    "medical_facility_notification": true,
                    "emergency_support_request": true
                  },
                  "medical_grade_compliance": true
                }
              },
              "risk_assessment": {
                "total_risk_score": 0.001359,
                "risk_level": "HIGH",
                "preparedness_score": 0.2,
                "preparedness_level": "NEEDS_IMPROVEMENT"
              },
              "ecosystem_integration": {
                "graviton_manufacturing_coordination": true,
                "medical_grade_protocols": true,
                "crew_safety_margin": 1000000000000.0
              }
            }
          }
        },
        "integration_assessment": {
          "integration_scores": {
            "lqg_coupling": 0.5601302190309042,
            "sif_coordination": 0.7967023589022377,
            "emergency_preparedness": 0.2,
            "safety": 0.0001,
            "energy_efficiency": 0.9278350515463918,
            "medical_compliance": 1.0
          },
          "overall_integration_score": 0.5807946049132556,
          "integration_complexity": 2.8,
          "integration_rating": "MARGINAL"
        },
        "recommendations": {
          "integration_feasible": "False",
          "critical_improvements": [
            "LQG polymer coupling optimization required",
            "Emergency protocol refinement necessary",
            "Safety margin enhancement critical"
          ],
          "optimization_strategies": [
            "Implement golden ratio field harmonics for enhanced coupling",
            "Establish redundant field monitoring systems",
            "Integrate with graviton manufacturing ecosystem protocols",
            "Develop adaptive field strength management",
            "Create real-time integration health monitoring"
          ],
          "next_steps": [
            "Fundamental integration redesign required",
            "Extensive R&D for critical improvements",
            "Safety protocol complete overhaul"
          ]
        },
        "uq_resolution": {
          "concern_id": "UQ-INTEGRATION-001",
          "status": "IMPLEMENTED",
          "validation_score": 0.5807946049132556,
          "resolution_date": "2025-07-11T19:47:06.274156",
          "notes": "Comprehensive hull-field integration analysis complete for FTL vessel operation"
        }
      }
    },
    "medium_vessel": {
      "comprehensive_integration_assessment": {
        "assessment_info": {
          "vessel_type": "medium_vessel",
          "assessment_date": "2025-07-11T19:47:06.275660",
          "vessel_configuration": {
            "dimensions": [
              100,
              20,
              5
            ],
            "crew_capacity": 50,
            "field_systems": [
              "FieldConfiguration(field_type=<FieldType.LQG_POLYMER: 'lqg_polymer'>, field_strength=0.7, coupling_strength=0.8, coherence_time=1e-06, energy_requirement=200, safety_margin=1000000000.0, integration_level=<IntegrationLevel.COMPLETE: 'complete'>)",
              "FieldConfiguration(field_type=<FieldType.STRUCTURAL_INTEGRITY: 'structural_integrity'>, field_strength=0.8, coupling_strength=0.9, coherence_time=0.001, energy_requirement=100, safety_margin=100000000.0, integration_level=<IntegrationLevel.COMPLETE: 'complete'>)",
              "FieldConfiguration(field_type=<FieldType.WARP_BUBBLE: 'warp_bubble'>, field_strength=0.6, coupling_strength=0.7, coherence_time=1e-05, energy_requirement=500, safety_margin=10000000000.0, integration_level=<IntegrationLevel.QUANTUM_COHERENT: 'quantum_coherent'>)",
              "FieldConfiguration(field_type=<FieldType.ARTIFICIAL_GRAVITY: 'artificial_gravity'>, field_strength=0.5, coupling_strength=0.6, coherence_time=0.01, energy_requirement=30, safety_margin=10000000.0, integration_level=<IntegrationLevel.ADVANCED: 'advanced'>)"
            ],
            "hull_material": "graphene_metamaterial",
            "safety_protocol": "SafetyProtocol.FTL_GRADE"
          },
          "graviton_ecosystem_integration": true
        },
        "individual_analyses": {
          "lqg_polymer_coupling": {
            "lqg_polymer_coupling_analysis": {
              "input_parameters": {
                "hull_material": "graphene_metamaterial",
                "field_strength": 0.7,
                "polymer_discretization_scale_m": 1e-15
              },
              "coupling_characteristics": {
                "quantum_coupling_strength": 0.6649999999999999,
                "discretization_coupling_factor": 1.1111111110987658e-11,
                "enhanced_coupling_efficiency": 0.8277479903456696,
                "golden_ratio_enhancement": 24473.382006867614
              },
              "energy_analysis": {
                "polymer_energy_density_j_per_m3": 3642224060.3394284,
                "hull_stress_induced_pa": 134897.18741848003,
                "field_penetration_depth_m": 8.154753215150047e-15
              },
              "coherence_analysis": {
                "base_coherence_time_s": 1e-06,
                "hull_decoherence_rate": 0.03500000000000003,
                "effective_coherence_time_s": 9.661835748792269e-07,
                "coherence_preservation": 0.9661835748792269
              },
              "resonance_analysis": {
                "resonance_frequencies_hz": [
                  1.8381454968069433e+22,
                  3.6762909936138865e+22,
                  5.514436490420829e+22,
                  7.352581987227773e+22,
                  9.190727484034717e+22
                ],
                "resonance_risk_level": "MEDIUM"
              },
              "safety_assessment": {
                "crew_exposure_estimate": 3.6422240603394286e-06,
                "crew_safety_factor": 2.7455751854728214e+17,
                "medical_grade_compliant": true,
                "safety_level": "EXCELLENT"
              }
            }
          },
          "sif_integration": {
            "sif_integration_analysis": {
              "sif_parameters": {
                "baseline_strength": 0.8,
                "coverage_efficiency": 0.95,
                "response_time_s": 0.001
              },
              "field_interactions": {
                "lqg_polymer": {
                  "interaction_strength": 0.44799999999999995,
                  "interference_pattern": "quantum_coupled",
                  "energy_requirement_mw": 97.99999999999999,
                  "stress_enhancement_factor": 0.250752,
                  "safety_margin": 2232142857.1428576,
                  "integration_level": "complete"
                },
                "structural_integrity": {
                  "interaction_strength": 1.6,
                  "interference_pattern": "constructive",
                  "energy_requirement_mw": 80.0,
                  "stress_enhancement_factor": 0.27840000000000004,
                  "safety_margin": 62500000.0,
                  "integration_level": "complete"
                },
                "warp_bubble": {
                  "interaction_strength": 0.33599999999999997,
                  "interference_pattern": "geometric",
                  "energy_requirement_mw": 107.99999999999999,
                  "stress_enhancement_factor": 0.248064,
                  "safety_margin": 29761904761.904766,
                  "integration_level": "quantum_coherent"
                },
                "artificial_gravity": {
                  "interaction_strength": 0.2,
                  "interference_pattern": "electromagnetic",
                  "energy_requirement_mw": 7.5,
                  "stress_enhancement_factor": 0.2448,
                  "safety_margin": 50000000.0,
                  "integration_level": "advanced"
                }
              },
              "system_analysis": {
                "total_energy_requirement_mw": 293.5,
                "coordination_efficiency": 0.5555555555555556,
                "optimized_coordination_efficiency": 0.5678021195161522,
                "maximum_stress_enhancement": 0.27840000000000004,
                "minimum_safety_margin": 50000000.0,
                "worst_case_shutdown_time_s": 0.16666666666666669
              },
              "coupling_analysis": {
                "coupling_matrix": [
                  [
                    1.0,
                    0.36000000000000004,
                    0.504,
                    0.24
                  ],
                  [
                    0.5760000000000001,
                    1.0,
                    0.504,
                    0.27
                  ],
                  [
                    0.27999999999999997,
                    0.315,
                    1.0,
                    0.21
                  ],
                  [
                    0.24,
                    0.27,
                    0.21,
                    1.0
                  ]
                ],
                "max_eigenvalue": 2.0008557884392584,
                "system_stable": "False",
                "stability_assessment": "UNSTABLE"
              },
              "golden_ratio_optimization": {
                "sif_enhancement_factor": 2204.3815129073973,
                "coordination_improvement": "2.2%"
              }
            }
          },
          "emergency_protocols": {
            "emergency_protocol_analysis": {
              "vessel_configuration": {
                "dimensions": [
                  100,
                  20,
                  5
                ],
                "crew_capacity": 50,
                "field_systems": [
                  "FieldConfiguration(field_type=<FieldType.LQG_POLYMER: 'lqg_polymer'>, field_strength=0.7, coupling_strength=0.8, coherence_time=1e-06, energy_requirement=200, safety_margin=1000000000.0, integration_level=<IntegrationLevel.COMPLETE: 'complete'>)",
                  "FieldConfiguration(field_type=<FieldType.STRUCTURAL_INTEGRITY: 'structural_integrity'>, field_strength=0.8, coupling_strength=0.9, coherence_time=0.001, energy_requirement=100, safety_margin=100000000.0, integration_level=<IntegrationLevel.COMPLETE: 'complete'>)",
                  "FieldConfiguration(field_type=<FieldType.WARP_BUBBLE: 'warp_bubble'>, field_strength=0.6, coupling_strength=0.7, coherence_time=1e-05, energy_requirement=500, safety_margin=10000000000.0, integration_level=<IntegrationLevel.QUANTUM_COHERENT: 'quantum_coherent'>)",
                  "FieldConfiguration(field_type=<FieldType.ARTIFICIAL_GRAVITY: 'artificial_gravity'>, field_strength=0.5, coupling_strength=0.6, coherence_time=0.01, energy_requirement=30, safety_margin=10000000.0, integration_level=<IntegrationLevel.ADVANCED: 'advanced'>)"
                ],
                "hull_material": "graphene_metamaterial",
                "safety_protocol": "SafetyProtocol.FTL_GRADE"
              },
              "threat_scenarios": {
                "field_cascade_failure": {
                  "description": "Multiple field systems fail simultaneously",
                  "probability": 1e-06,
                  "severity": "CRITICAL",
                  "response_time_required": 0.1,
                  "crew_danger_level": "HIGH"
                },
                "hull_breach_with_field_loss": {
                  "description": "Hull breach causes field system failure",
                  "probability": 1e-07,
                  "severity": "CATASTROPHIC",
                  "response_time_required": 0.05,
                  "crew_danger_level": "EXTREME"
                },
                "lqg_polymer_instability": {
                  "description": "LQG polymer field becomes unstable",
                  "probability": 1e-05,
                  "severity": "HIGH",
                  "response_time_required": 0.5,
                  "crew_danger_level": "MEDIUM"
                },
                "sif_overload": {
                  "description": "Structural Integrity Field overloads",
                  "probability": 0.0001,
                  "severity": "MEDIUM",
                  "response_time_required": 1.0,
                  "crew_danger_level": "LOW"
                },
                "quantum_decoherence_event": {
                  "description": "Quantum coherence loss in field systems",
                  "probability": 0.001,
                  "severity": "LOW",
                  "response_time_required": 10.0,
                  "crew_danger_level": "MINIMAL"
                }
              },
              "response_protocols": {
                "field_cascade_failure": {
                  "threat_details": {
                    "description": "Multiple field systems fail simultaneously",
                    "probability": 1e-06,
                    "severity": "CRITICAL",
                    "response_time_required": 0.1,
                    "crew_danger_level": "HIGH"
                  },
                  "assigned_protocol": "emergency",
                  "response_time_analysis": {
                    "required_time_s": 0.1,
                    "available_time_s": 0.1,
                    "response_adequate": true,
                    "time_margin_s": 0.0
                  },
                  "response_actions": [
                    "Immediate field system isolation",
                    "Emergency power redistribution",
                    "Backup field activation",
                    "Complete system shutdown",
                    "Emergency life support",
                    "Distress signal transmission"
                  ],
                  "crew_protection_measures": [
                    "Immediate isolation chamber activation",
                    "Medical monitoring enhancement",
                    "Emergency medical preparation"
                  ],
                  "ecosystem_integration": {
                    "graviton_manufacturing_alerts": true,
                    "cross_system_coordination": true,
                    "medical_facility_notification": true,
                    "emergency_support_request": true
                  },
                  "medical_grade_compliance": true
                },
                "hull_breach_with_field_loss": {
                  "threat_details": {
                    "description": "Hull breach causes field system failure",
                    "probability": 1e-07,
                    "severity": "CATASTROPHIC",
                    "response_time_required": 0.05,
                    "crew_danger_level": "EXTREME"
                  },
                  "assigned_protocol": "emergency",
                  "response_time_analysis": {
                    "required_time_s": 0.05,
                    "available_time_s": 0.1,
                    "response_adequate": false,
                    "time_margin_s": 0.05
                  },
                  "response_actions": [
                    "Immediate field system isolation",
                    "Emergency power redistribution",
                    "Backup field activation",
                    "Hull breach containment",
                    "Emergency atmospheric systems",
                    "Crew evacuation protocols"
                  ],
                  "crew_protection_measures": [
                    "Immediate isolation chamber activation",
                    "Medical monitoring enhancement",
                    "Emergency medical preparation"
                  ],
                  "ecosystem_integration": {
                    "graviton_manufacturing_alerts": true,
                    "cross_system_coordination": true,
                    "medical_facility_notification": true,
                    "emergency_support_request": true
                  },
                  "medical_grade_compliance": true
                },
                "lqg_polymer_instability": {
                  "threat_details": {
                    "description": "LQG polymer field becomes unstable",
                    "probability": 1e-05,
                    "severity": "HIGH",
                    "response_time_required": 0.5,
                    "crew_danger_level": "MEDIUM"
                  },
                  "assigned_protocol": "ftl_grade",
                  "response_time_analysis": {
                    "required_time_s": 0.5,
                    "available_time_s": 3,
                    "response_adequate": false,
                    "time_margin_s": 2.5
                  },
                  "response_actions": [],
                  "crew_protection_measures": [
                    "Enhanced radiation shielding",
                    "Medical monitoring increase"
                  ],
                  "ecosystem_integration": {
                    "graviton_manufacturing_alerts": true,
                    "cross_system_coordination": true,
                    "medical_facility_notification": true,
                    "emergency_support_request": true
                  },
                  "medical_grade_compliance": true
                },
                "sif_overload": {
                  "threat_details": {
                    "description": "Structural Integrity Field overloads",
                    "probability": 0.0001,
                    "severity": "MEDIUM",
                    "response_time_required": 1.0,
                    "crew_danger_level": "LOW"
                  },
                  "assigned_protocol": "medical_grade",
                  "response_time_analysis": {
                    "required_time_s": 1.0,
                    "available_time_s": 30,
                    "response_adequate": false,
                    "time_margin_s": 29.0
                  },
                  "response_actions": [],
                  "crew_protection_measures": [
                    "Standard monitoring continuation"
                  ],
                  "ecosystem_integration": {
                    "graviton_manufacturing_alerts": true,
                    "cross_system_coordination": true,
                    "medical_facility_notification": true,
                    "emergency_support_request": true
                  },
                  "medical_grade_compliance": true
                },
                "quantum_decoherence_event": {
                  "threat_details": {
                    "description": "Quantum coherence loss in field systems",
                    "probability": 0.001,
                    "severity": "LOW",
                    "response_time_required": 10.0,
                    "crew_danger_level": "MINIMAL"
                  },
                  "assigned_protocol": "medical_grade",
                  "response_time_analysis": {
                    "required_time_s": 10.0,
                    "available_time_s": 30,
                    "response_adequate": false,
                    "time_margin_s": 20.0
                  },
                  "response_actions": [],
                  "crew_protection_measures": [
                    "Standard monitoring continuation"
                  ],
                  "ecosystem_integration": {
                    "graviton_manufacturing_alerts": true,
                    "cross_system_coordination": true,
                    "medical_facility_notification": true,
                    "emergency_support_request": true
                  },
                  "medical_grade_compliance": true
                }
              },
              "risk_assessment": {
                "total_risk_score": 0.001359,
                "risk_level": "HIGH",
                "preparedness_score": 0.2,
                "preparedness_level": "NEEDS_IMPROVEMENT"
              },
              "ecosystem_integration": {
                "graviton_manufacturing_coordination": true,
                "medical_grade_protocols": true,
                "crew_safety_margin": 1000000000000.0
              }
            }
          }
        },
        "integration_assessment": {
          "integration_scores": {
            "lqg_coupling": 0.8277479903456696,
            "sif_coordination": 0.5678021195161522,
            "emergency_preparedness": 0.2,
            "safety": 0.01,
            "energy_efficiency": 0.991768322919766,
            "medical_compliance": 1.0
          },
          "overall_integration_score": 0.5995530721302647,
          "integration_complexity": 10.4,
          "integration_rating": "MARGINAL"
        },
        "recommendations": {
          "integration_feasible": "False",
          "critical_improvements": [
            "SIF coordination enhancement needed",
            "Emergency protocol refinement necessary",
            "Safety margin enhancement critical"
          ],
          "optimization_strategies": [
            "Implement golden ratio field harmonics for enhanced coupling",
            "Establish redundant field monitoring systems",
            "Integrate with graviton manufacturing ecosystem protocols",
            "Develop adaptive field strength management",
            "Create real-time integration health monitoring"
          ],
          "next_steps": [
            "Fundamental integration redesign required",
            "Extensive R&D for critical improvements",
            "Safety protocol complete overhaul"
          ]
        },
        "uq_resolution": {
          "concern_id": "UQ-INTEGRATION-001",
          "status": "IMPLEMENTED",
          "validation_score": 0.5995530721302647,
          "resolution_date": "2025-07-11T19:47:06.275660",
          "notes": "Comprehensive hull-field integration analysis complete for FTL vessel operation"
        }
      }
    },
    "large_vessel": {
      "comprehensive_integration_assessment": {
        "assessment_info": {
          "vessel_type": "large_vessel",
          "assessment_date": "2025-07-11T19:47:06.276925",
          "vessel_configuration": {
            "dimensions": [
              200,
              40,
              10
            ],
            "crew_capacity": 200,
            "field_systems": [
              "FieldConfiguration(field_type=<FieldType.LQG_POLYMER: 'lqg_polymer'>, field_strength=0.8, coupling_strength=0.9, coherence_time=1e-06, energy_requirement=800, safety_margin=1000000000000.0, integration_level=<IntegrationLevel.QUANTUM_COHERENT: 'quantum_coherent'>)",
              "FieldConfiguration(field_type=<FieldType.STRUCTURAL_INTEGRITY: 'structural_integrity'>, field_strength=0.9, coupling_strength=0.95, coherence_time=0.001, energy_requirement=400, safety_margin=100000000000.0, integration_level=<IntegrationLevel.QUANTUM_COHERENT: 'quantum_coherent'>)",
              "FieldConfiguration(field_type=<FieldType.WARP_BUBBLE: 'warp_bubble'>, field_strength=0.7, coupling_strength=0.8, coherence_time=1e-05, energy_requirement=2000, safety_margin=1000000000000.0, integration_level=<IntegrationLevel.QUANTUM_COHERENT: 'quantum_coherent'>)",
              "FieldConfiguration(field_type=<FieldType.ARTIFICIAL_GRAVITY: 'artificial_gravity'>, field_strength=0.6, coupling_strength=0.7, coherence_time=0.01, energy_requirement=120, safety_margin=10000000000.0, integration_level=<IntegrationLevel.COMPLETE: 'complete'>)",
              "FieldConfiguration(field_type=<FieldType.ELECTROMAGNETIC_SHIELD: 'electromagnetic_shield'>, field_strength=0.9, coupling_strength=0.8, coherence_time=0.1, energy_requirement=50, safety_margin=100000000.0, integration_level=<IntegrationLevel.ADVANCED: 'advanced'>)"
            ],
            "hull_material": "graphene_metamaterial",
            "safety_protocol": "SafetyProtocol.FTL_GRADE"
          },
          "graviton_ecosystem_integration": true
        },
        "individual_analyses": {
          "lqg_polymer_coupling": {
            "lqg_polymer_coupling_analysis": {
              "input_parameters": {
                "hull_material": "graphene_metamaterial",
                "field_strength": 0.8,
                "polymer_discretization_scale_m": 1e-15
              },
              "coupling_characteristics": {
                "quantum_coupling_strength": 0.76,
                "discretization_coupling_factor": 1.1111111110987658e-11,
                "enhanced_coupling_efficiency": 0.9459977032521939,
                "golden_ratio_enhancement": 24473.382006867614
              },
              "energy_analysis": {
                "polymer_energy_density_j_per_m3": 4757190609.422928,
                "hull_stress_induced_pa": 176192.24479148415,
                "field_penetration_depth_m": 8.717797887081349e-15
              },
              "coherence_analysis": {
                "base_coherence_time_s": 1e-06,
                "hull_decoherence_rate": 0.040000000000000036,
                "effective_coherence_time_s": 9.615384615384615e-07,
                "coherence_preservation": 0.9615384615384616
              },
              "resonance_analysis": {
                "resonance_frequencies_hz": [
                  1.7194276690232389e+22,
                  3.4388553380464777e+22,
                  5.158283007069716e+22,
                  6.8777106760929554e+22,
                  8.597138345116195e+22
                ],
                "resonance_risk_level": "MEDIUM"
              },
              "safety_assessment": {
                "crew_exposure_estimate": 4.757190609422928e-06,
                "crew_safety_factor": 2.1020810013776288e+17,
                "medical_grade_compliant": true,
                "safety_level": "EXCELLENT"
              }
            }
          },
          "sif_integration": {
            "sif_integration_analysis": {
              "sif_parameters": {
                "baseline_strength": 0.8,
                "coverage_efficiency": 0.95,
                "response_time_s": 0.001
              },
              "field_interactions": {
                "lqg_polymer": {
                  "interaction_strength": 0.5760000000000002,
                  "interference_pattern": "quantum_coupled",
                  "energy_requirement_mw": 512.0000000000001,
                  "stress_enhancement_factor": 0.253824,
                  "safety_margin": 1736111111111.1106,
                  "integration_level": "quantum_coherent"
                },
                "structural_integrity": {
                  "interaction_strength": 1.8,
                  "interference_pattern": "constructive",
                  "energy_requirement_mw": 360.0,
                  "stress_enhancement_factor": 0.28319999999999995,
                  "safety_margin": 55555555555.55556,
                  "integration_level": "quantum_coherent"
                },
                "warp_bubble": {
                  "interaction_strength": 0.39199999999999996,
                  "interference_pattern": "geometric",
                  "energy_requirement_mw": 685.9999999999999,
                  "stress_enhancement_factor": 0.24940799999999996,
                  "safety_margin": 2551020408163.2656,
                  "integration_level": "quantum_coherent"
                },
                "artificial_gravity": {
                  "interaction_strength": 0.24,
                  "interference_pattern": "electromagnetic",
                  "energy_requirement_mw": 43.199999999999996,
                  "stress_enhancement_factor": 0.24576,
                  "safety_margin": 41666666666.66667,
                  "integration_level": "complete"
                },
                "electromagnetic_shield": {
                  "interaction_strength": 0.36000000000000004,
                  "interference_pattern": "electromagnetic",
                  "energy_requirement_mw": 45.0,
                  "stress_enhancement_factor": 0.24864,
                  "safety_margin": 277777777.77777773,
                  "integration_level": "advanced"
                }
              },
              "system_analysis": {
                "total_energy_requirement_mw": 1646.2,
                "coordination_efficiency": 0.4721359549995794,
                "optimized_coordination_efficiency": 0.48254363270737893,
                "maximum_stress_enhancement": 0.28319999999999995,
                "minimum_safety_margin": 277777777.77777773,
                "worst_case_shutdown_time_s": 0.14285714285714288
              },
              "coupling_analysis": {
                "coupling_matrix": [
                  [
                    1.0,
                    0.4275,
                    0.6480000000000001,
                    0.315,
                    0.36000000000000004
                  ],
                  [
                    0.684,
                    1.0,
                    0.6080000000000001,
                    0.33249999999999996,
                    0.38
                  ],
                  [
                    0.36000000000000004,
                    0.38,
                    1.0,
                    0.27999999999999997,
                    0.32000000000000006
                  ],
                  [
                    0.315,
                    0.33249999999999996,
                    0.27999999999999997,
                    1.0,
                    0.27999999999999997
                  ],
                  [
                    0.36000000000000004,
                    0.38,
                    0.32000000000000006,
                    0.27999999999999997,
                    1.0
                  ]
                ],
                "max_eigenvalue": 2.540777578549141,
                "system_stable": "False",
                "stability_assessment": "UNSTABLE"
              },
              "golden_ratio_optimization": {
                "sif_enhancement_factor": 2204.3815129073973,
                "coordination_improvement": "2.2%"
              }
            }
          },
          "emergency_protocols": {
            "emergency_protocol_analysis": {
              "vessel_configuration": {
                "dimensions": [
                  200,
                  40,
                  10
                ],
                "crew_capacity": 200,
                "field_systems": [
                  "FieldConfiguration(field_type=<FieldType.LQG_POLYMER: 'lqg_polymer'>, field_strength=0.8, coupling_strength=0.9, coherence_time=1e-06, energy_requirement=800, safety_margin=1000000000000.0, integration_level=<IntegrationLevel.QUANTUM_COHERENT: 'quantum_coherent'>)",
                  "FieldConfiguration(field_type=<FieldType.STRUCTURAL_INTEGRITY: 'structural_integrity'>, field_strength=0.9, coupling_strength=0.95, coherence_time=0.001, energy_requirement=400, safety_margin=100000000000.0, integration_level=<IntegrationLevel.QUANTUM_COHERENT: 'quantum_coherent'>)",
                  "FieldConfiguration(field_type=<FieldType.WARP_BUBBLE: 'warp_bubble'>, field_strength=0.7, coupling_strength=0.8, coherence_time=1e-05, energy_requirement=2000, safety_margin=1000000000000.0, integration_level=<IntegrationLevel.QUANTUM_COHERENT: 'quantum_coherent'>)",
                  "FieldConfiguration(field_type=<FieldType.ARTIFICIAL_GRAVITY: 'artificial_gravity'>, field_strength=0.6, coupling_strength=0.7, coherence_time=0.01, energy_requirement=120, safety_margin=10000000000.0, integration_level=<IntegrationLevel.COMPLETE: 'complete'>)",
                  "FieldConfiguration(field_type=<FieldType.ELECTROMAGNETIC_SHIELD: 'electromagnetic_shield'>, field_strength=0.9, coupling_strength=0.8, coherence_time=0.1, energy_requirement=50, safety_margin=100000000.0, integration_level=<IntegrationLevel.ADVANCED: 'advanced'>)"
                ],
                "hull_material": "graphene_metamaterial",
                "safety_protocol": "SafetyProtocol.FTL_GRADE"
              },
              "threat_scenarios": {
                "field_cascade_failure": {
                  "description": "Multiple field systems fail simultaneously",
                  "probability": 1e-06,
                  "severity": "CRITICAL",
                  "response_time_required": 0.1,
                  "crew_danger_level": "HIGH"
                },
                "hull_breach_with_field_loss": {
                  "description": "Hull breach causes field system failure",
                  "probability": 1e-07,
                  "severity": "CATASTROPHIC",
                  "response_time_required": 0.05,
                  "crew_danger_level": "EXTREME"
                },
                "lqg_polymer_instability": {
                  "description": "LQG polymer field becomes unstable",
                  "probability": 1e-05,
                  "severity": "HIGH",
                  "response_time_required": 0.5,
                  "crew_danger_level": "MEDIUM"
                },
                "sif_overload": {
                  "description": "Structural Integrity Field overloads",
                  "probability": 0.0001,
                  "severity": "MEDIUM",
                  "response_time_required": 1.0,
                  "crew_danger_level": "LOW"
                },
                "quantum_decoherence_event": {
                  "description": "Quantum coherence loss in field systems",
                  "probability": 0.001,
                  "severity": "LOW",
                  "response_time_required": 10.0,
                  "crew_danger_level": "MINIMAL"
                }
              },
              "response_protocols": {
                "field_cascade_failure": {
                  "threat_details": {
                    "description": "Multiple field systems fail simultaneously",
                    "probability": 1e-06,
                    "severity": "CRITICAL",
                    "response_time_required": 0.1,
                    "crew_danger_level": "HIGH"
                  },
                  "assigned_protocol": "emergency",
                  "response_time_analysis": {
                    "required_time_s": 0.1,
                    "available_time_s": 0.1,
                    "response_adequate": true,
                    "time_margin_s": 0.0
                  },
                  "response_actions": [
                    "Immediate field system isolation",
                    "Emergency power redistribution",
                    "Backup field activation",
                    "Complete system shutdown",
                    "Emergency life support",
                    "Distress signal transmission"
                  ],
                  "crew_protection_measures": [
                    "Immediate isolation chamber activation",
                    "Medical monitoring enhancement",
                    "Emergency medical preparation"
                  ],
                  "ecosystem_integration": {
                    "graviton_manufacturing_alerts": true,
                    "cross_system_coordination": true,
                    "medical_facility_notification": true,
                    "emergency_support_request": true
                  },
                  "medical_grade_compliance": true
                },
                "hull_breach_with_field_loss": {
                  "threat_details": {
                    "description": "Hull breach causes field system failure",
                    "probability": 1e-07,
                    "severity": "CATASTROPHIC",
                    "response_time_required": 0.05,
                    "crew_danger_level": "EXTREME"
                  },
                  "assigned_protocol": "emergency",
                  "response_time_analysis": {
                    "required_time_s": 0.05,
                    "available_time_s": 0.1,
                    "response_adequate": false,
                    "time_margin_s": 0.05
                  },
                  "response_actions": [
                    "Immediate field system isolation",
                    "Emergency power redistribution",
                    "Backup field activation",
                    "Hull breach containment",
                    "Emergency atmospheric systems",
                    "Crew evacuation protocols"
                  ],
                  "crew_protection_measures": [
                    "Immediate isolation chamber activation",
                    "Medical monitoring enhancement",
                    "Emergency medical preparation"
                  ],
                  "ecosystem_integration": {
                    "graviton_manufacturing_alerts": true,
                    "cross_system_coordination": true,
                    "medical_facility_notification": true,
                    "emergency_support_request": true
                  },
                  "medical_grade_compliance": true
                },
                "lqg_polymer_instability": {
                  "threat_details": {
                    "description": "LQG polymer field becomes unstable",
                    "probability": 1e-05,
                    "severity": "HIGH",
                    "response_time_required": 0.5,
                    "crew_danger_level": "MEDIUM"
                  },
                  "assigned_protocol": "ftl_grade",
                  "response_time_analysis": {
                    "required_time_s": 0.5,
                    "available_time_s": 3,
                    "response_adequate": false,
                    "time_margin_s": 2.5
                  },
                  "response_actions": [],
                  "crew_protection_measures": [
                    "Enhanced radiation shielding",
                    "Medical monitoring increase"
                  ],
                  "ecosystem_integration": {
                    "graviton_manufacturing_alerts": true,
                    "cross_system_coordination": true,
                    "medical_facility_notification": true,
                    "emergency_support_request": true
                  },
                  "medical_grade_compliance": true
                },
                "sif_overload": {
                  "threat_details": {
                    "description": "Structural Integrity Field overloads",
                    "probability": 0.0001,
                    "severity": "MEDIUM",
                    "response_time_required": 1.0,
                    "crew_danger_level": "LOW"
                  },
                  "assigned_protocol": "medical_grade",
                  "response_time_analysis": {
                    "required_time_s": 1.0,
                    "available_time_s": 30,
                    "response_adequate": false,
                    "time_margin_s": 29.0
                  },
                  "response_actions": [],
                  "crew_protection_measures": [
                    "Standard monitoring continuation"
                  ],
                  "ecosystem_integration": {
                    "graviton_manufacturing_alerts": true,
                    "cross_system_coordination": true,
                    "medical_facility_notification": true,
                    "emergency_support_request": true
                  },
                  "medical_grade_compliance": true
                },
                "quantum_decoherence_event": {
                  "threat_details": {
                    "description": "Quantum coherence loss in field systems",
                    "probability": 0.001,
                    "severity": "LOW",
                    "response_time_required": 10.0,
                    "crew_danger_level": "MINIMAL"
                  },
                  "assigned_protocol": "medical_grade",
                  "response_time_analysis": {
                    "required_time_s": 10.0,
                    "available_time_s": 30,
                    "response_adequate": false,
                    "time_margin_s": 20.0
                  },
                  "response_actions": [],
                  "crew_protection_measures": [
                    "Standard monitoring continuation"
                  ],
                  "ecosystem_integration": {
                    "graviton_manufacturing_alerts": true,
                    "cross_system_coordination": true,
                    "medical_facility_notification": true,
                    "emergency_support_request": true
                  },
                  "medical_grade_compliance": true
                }
              },
              "risk_assessment": {
                "total_risk_score": 0.001359,
                "risk_level": "HIGH",
                "preparedness_score": 0.2,
                "preparedness_level": "NEEDS_IMPROVEMENT"
              },
              "ecosystem_integration": {
                "graviton_manufacturing_coordination": true,
                "medical_grade_protocols": true,
                "crew_safety_margin": 1000000000000.0
              }
            }
          }
        },
        "integration_assessment": {
          "integration_scores": {
            "lqg_coupling": 0.9459977032521939,
            "sif_coordination": 0.48254363270737893,
            "emergency_preparedness": 0.2,
            "safety": 0.1,
            "energy_efficiency": 0.995805170718349,
            "medical_compliance": 0.8
          },
          "overall_integration_score": 0.5873910844463204,
          "integration_complexity": 19.5,
          "integration_rating": "MARGINAL"
        },
        "recommendations": {
          "integration_feasible": "False",
          "critical_improvements": [
            "SIF coordination enhancement needed",
            "Emergency protocol refinement necessary",
            "Safety margin enhancement critical",
            "Medical-grade compliance enhancement needed"
          ],
          "optimization_strategies": [
            "Implement golden ratio field harmonics for enhanced coupling",
            "Establish redundant field monitoring systems",
            "Integrate with graviton manufacturing ecosystem protocols",
            "Develop adaptive field strength management",
            "Create real-time integration health monitoring"
          ],
          "next_steps": [
            "Fundamental integration redesign required",
            "Extensive R&D for critical improvements",
            "Safety protocol complete overhaul"
          ]
        },
        "uq_resolution": {
          "concern_id": "UQ-INTEGRATION-001",
          "status": "IMPLEMENTED",
          "validation_score": 0.5873910844463204,
          "resolution_date": "2025-07-11T19:47:06.276925",
          "notes": "Comprehensive hull-field integration analysis complete for FTL vessel operation"
        }
      }
    }
  },
  "validation": {
    "medical_grade_protocols": true,
    "sif_framework_integration": true,
    "crew_safety_margin": 1000000000000.0
  }
}